simplecoremidi/__init__.py
simplecoremidi/_simplecoremidi.c
simplecoremidi/_simplecoremidi.so
simplecoremidi/core.py
simplecoremidi/examples/__init__.py
simplecoremidi/examples/emitter.py
simplecoremidi/examples/play_a_scale.py
simplecoremidi/examples/repeater.py
simplecoremidi-0.3.dist-info/DESCRIPTION.rst
simplecoremidi-0.3.dist-info/entry_points.txt
simplecoremidi-0.3.dist-info/METADATA
simplecoremidi-0.3.dist-info/pydist.json
simplecoremidi-0.3.dist-info/RECORD
simplecoremidi-0.3.dist-info/top_level.txt
simplecoremidi-0.3.dist-info/WHEEL
