Metadata-Version: 2.0
Name: simplecoremidi
Version: 0.3
Summary: Simple OS X CoreMIDI interface
Home-page: https://github.com/sixohsix/simplecoremidi
Author: Mike Verdone
Author-email: mike.verdone+simplecoremidi@gmail.com
License: MIT License
Keywords: osx,CoreMIDI,MIDI,Mac OS X
Platform: UNKNOWN
Classifier: Programming Language :: Python :: 2.7
Classifier: Programming Language :: Python :: 3.3
Classifier: Environment :: MacOS X
Classifier: Intended Audience :: Developers
Classifier: Development Status :: 3 - Alpha
Classifier: Topic :: Multimedia :: Sound/Audio :: MIDI
Classifier: License :: OSI Approved :: MIT License
